{
    "metadata": {
        "author": "Zela",
        "description": "VBook extension của Zela"
    },
    "data": [
        {
            "name": "Kho truyện chữ - me",
            "author": "Zela",
            "path": "https://raw.githubusercontent.com/Zela87/Vbook/main/khotruyenchu-zela/plugin.zip",
            "version": 3,
            "source": "https://khotruyenchu.me",
            "icon": "https://raw.githubusercontent.com/Zela87/Vbook/main/khotruyenchu-zela/icon.png",
            "description": "Đọc truyện trên khotruyenchu.me",
            "type": "novel",
            "locale": "vi_VN"
        },
        {
            "name": "Kho truyện chữ - space",
            "author": "Zela",
            "path": "https://raw.githubusercontent.com/Zela87/Vbook/main/khotruyenchu-space/plugin.zip",
            "version": 1,
            "source": "https://khotruyenchu.space",
            "icon": "https://raw.githubusercontent.com/Zela87/Vbook/main/khotruyenchu-space/icon.png",
            "description": "Đọc truyện trên khotruyenchu.space",
            "type": "novel",
            "locale": "vi_VN"
        },
        {
            "name": "HentaiVN-XX",
            "author": "Zela",
            "path": "https://raw.githubusercontent.com/Zela87/Vbook/main/htvnxx/plugin.zip",
            "version": 2,
            "source": "https://www.hentaivnxx.com",
            "icon": "https://raw.githubusercontent.com/Zela87/Vbook/main/htvnxx/icon.png",
            "description": "Đọc truyện trên trang Truyện Hentaivnxx.com",
            "type": "comic",
            "locale": "vi_VN",
            "tag": "nsfw"
        },
        {
            "name": "HentaiVN-social",
            "author": "Zela",
            "path": "https://raw.githubusercontent.com/Zela87/Vbook/main/htvn-social/plugin.zip",
            "version": 1,
            "source": "https://hentaivn.social",
            "icon": "https://raw.githubusercontent.com/Zela87/Vbook/main/htvn-social/icon.png",
            "description": "Đọc truyện trên trang Truyện Hentaivn.social",
            "type": "comic",
            "locale": "vi_VN",
            "tag": "nsfw"
        },
        {
            "name": "HentaiVN-live",
            "author": "Zela",
            "path": "https://raw.githubusercontent.com/Zela87/Vbook/main/htvn-live/plugin.zip",
            "version": 1,
            "source": "https://www.hentaivnx.live",
            "icon": "https://raw.githubusercontent.com/Zela87/Vbook/main/htvn-live/icon.png",
            "description": "Đọc truyện trên trang Truyện Hentaivnx.live",
            "type": "comic",
            "locale": "vi_VN",
            "tag": "nsfw"
        },
        {
            "name": "Dâm cô nương",
            "author": "Zela",
            "path": "https://raw.githubusercontent.com/Zela87/Vbook/main/damconuong/plugin.zip",
            "version": 3,
            "source": "https://damconuong.ceo",
            "icon": "https://raw.githubusercontent.com/Zela87/Vbook/main/damconuong/icon.png",
            "description": "Đọc truyện trên trang Truyện Dâm cô nương",
            "type": "comic",
            "locale": "vi_VN",
            "tag": "nsfw"
        },
        {
            "name": "wnacg",
            "author": "Zela",
            "path": "https://raw.githubusercontent.com/Zela87/Vbook/main/wnacg/plugin.zip",
            "version": 1,
            "source": "https://wnacg.com",
            "icon": "https://raw.githubusercontent.com/Zela87/Vbook/main/wnacg/icon.png",
            "description": "Đọc truyện trên trang Truyện Dâm cô nương",
            "type": "comic",
            "locale": "vi_VN",
            "tag": "nsfw"
        },
        {
            "name": "SS Truyện",
            "author": "Zela",
            "path": "https://raw.githubusercontent.com/Zela87/Vbook/main/sstruyen-zela/plugin.zip",
            "version": 5,
            "source": "https://sstruyen.com.vn",
            "icon": "https://raw.githubusercontent.com/Zela87/Vbook/main/sstruyen-zela/icon.png",
            "description": "Đọc truyện trên trang SS Truyện",
            "type": "novel",
            "locale": "vi_VN"
        }
    ]
}